[
	{
		"__TYPE__": "SharedSliceContent",
		"variation": "default",
		"primary": {
			"heading": {
				"__TYPE__": "StructuredTextContent",
				"value": [
					{
						"type": "heading1",
						"content": {
							"text": "Search"
						}
					}
				]
			},
			"description": {
				"__TYPE__": "StructuredTextContent",
				"value": [
					{
						"type": "paragraph",
						"content": {
							"text": "Ea ipsum duis sit est ea elit minim culpa commodo minim cillum aute excepteur."
						}
					}
				]
			},
			"subheading": {
				"__TYPE__": "StructuredTextContent",
				"value": [
					{
						"type": "heading2",
						"content": {
							"text": "Cowboy"
						}
					}
				]
			}
		},
		"items": [
			{
				"__TYPE__": "GroupItemContent",
				"value": [
					[
						"features",
						{
							"__TYPE__": "StructuredTextContent",
							"value": [
								{
									"type": "heading4",
									"content": {
										"text": "Ranch"
									}
								}
							]
						}
					]
				]
			}
		]
	}
]